Autograder/README.md
Autograder/__init__.py
Autograder/ai_helper.py
Autograder/assignment.py
Autograder/docker_utils.py
Autograder/exceptions.py
Autograder/grade_assignments.py
Autograder/grader.py
Autograder/logging.yaml
Autograder/registry.py
Autograder/graders/__init__.py
Autograder/graders/docker_graders.py
Autograder/graders/manual.py
Autograder/graders/quiz_grader.py
Autograder/graders/text_submission_grader.py
Autograder/lms_interface/__init__.py
Autograder/lms_interface/canvas_interface.py
Autograder/lms_interface/classes.py
otter_autograder-0.3.1.dist-info/METADATA
otter_autograder-0.3.1.dist-info/WHEEL
otter_autograder-0.3.1.dist-info/entry_points.txt
otter_autograder-0.3.1.dist-info/licenses/LICENSE
otter_autograder-0.3.1.dist-info/RECORD
