Metadata-Version: 2.4
Name: Otter-Autograder
Version: 0.3.1
Summary: A collection of tools for grading homework automatically
Project-URL: Homepage, https://github.com/OtterDen-Lab/Autograder
Project-URL: Documentation, https://github.com/OtterDen-Lab/Autograder/tree/main/documentation
Project-URL: Repository, https://github.com/OtterDen-Lab/Autograder
Project-URL: Bug Tracker, https://github.com/OtterDen-Lab/Autograder/issues
Author-email: Sam Ogden <samuel.s.ogden@gmail.com>
License:                     GNU GENERAL PUBLIC LICENSE
License-File: LICENSE
Keywords: assessment,canvas,education,exam,lms,quiz,teaching,testing
Classifier: Development Status :: 4 - Beta
Classifier: Intended Audience :: Education
Classifier: License :: OSI Approved :: GNU General Public License v3 or later (GPLv3+)
Classifier: Programming Language :: Python :: 3
Classifier: Programming Language :: Python :: 3.12
Classifier: Topic :: Education :: Testing
Requires-Python: >=3.12
Requires-Dist: anthropic
Requires-Dist: bcrypt>=4.0.0
Requires-Dist: colorama
Requires-Dist: docker>=6.1.3
Requires-Dist: fastapi>=0.104.0
Requires-Dist: fuzzywuzzy
Requires-Dist: ollama>=0.6.0
Requires-Dist: openai
Requires-Dist: opencv-python>=4.8.0
Requires-Dist: pandas
Requires-Dist: pillow>=10.0.0
Requires-Dist: pydantic>=2.0.0
Requires-Dist: pymupdf
Requires-Dist: python-dotenv==1.0.1
Requires-Dist: python-levenshtein>=0.21.0
Requires-Dist: python-multipart>=0.0.6
Requires-Dist: pyyaml==6.0.1
Requires-Dist: pyzbar>=0.1.9
Requires-Dist: quizgenerator>=0.4.2
Requires-Dist: requests==2.32.2
Requires-Dist: scikit-learn
Requires-Dist: slack-sdk>=3.36.0
Requires-Dist: uvicorn[standard]>=0.24.0
Provides-Extra: dev
Requires-Dist: httpx>=0.25.2; extra == 'dev'
Requires-Dist: pytest>=7.4.3; extra == 'dev'
